dm_core/__init__.py
dm_core/meta/__init__.py
dm_core/meta/apps.py
dm_core/meta/auth_app_client.py
dm_core/meta/authentication.py
dm_core/meta/cas.py
dm_core/meta/decorator.py
dm_core/meta/errors.py
dm_core/meta/exceptions.py
dm_core/meta/filters.py
dm_core/meta/middleware.py
dm_core/meta/models.py
dm_core/meta/pagination.py
dm_core/meta/serializers.py
dm_core/meta/service.py
dm_core/meta/urls.py
dm_core/meta/users.py
dm_core/meta/utils.py
dm_core/meta/views.py
dm_core/meta/management/commands/__init__.py
dm_core/meta/management/commands/load.py
dm_core/meta/migrations/0001_initial.py
dm_core/meta/migrations/__init__.py
dm_core/meta/tests/__init__.py
dm_core/meta/tests/utils.py
dm_core_meta-1.0.1.dist-info/licenses/LICENSE
dm_core_meta-1.0.1.dist-info/METADATA
dm_core_meta-1.0.1.dist-info/WHEEL
dm_core_meta-1.0.1.dist-info/top_level.txt
dm_core_meta-1.0.1.dist-info/RECORD
